[{"_path":"/usages/ai-generation","_dir":"usages","_draft":false,"_partial":false,"_locale":"","title":"Ai Text & Image Generation","description":"Our new AI feature in MagicLMS allows users to create detailed descriptions and relevant images simply by providing an explanation.\nThis powerful tool enhances course creation by streamlining content generation, saving time, and ensuring engaging visuals for learners.","_type":"markdown","_id":"content:3.usages:05.ai-generation.md","_source":"content","_file":"3.usages/05.ai-generation.md","_stem":"3.usages/05.ai-generation","_extension":"md"},{"_path":"/usages/user-management","_dir":"usages","_draft":false,"_partial":false,"_locale":"","title":"User Management","description":"Effortlessly manage admins, instructors, and students with dedicated panels in magicLMS. Assign roles, track progress, and maintain control—all in one intuitive platform! 👥","_type":"markdown","_id":"content:3.usages:07.user-management.md","_source":"content","_file":"3.usages/07.user-management.md","_stem":"3.usages/07.user-management","_extension":"md"}]