{"id":"0fa05271-9a74-4a57-b85f-6788bad04191","timestamp":1740990890767,"matcher":{"static":{"/api/search":{"prerender":true}},"wildcard":{},"dynamic":{}},"prerendered":["/","/getting-started/introduction","/getting-started/installation","/usages/instructor-package","/usages/instructor-payment","/usages/admin-earning","/getting-started/installation/cpanel-setup","/configuration/payment-setup","/configuration/zoom-class-setup","/getting-started/installation/application-setup","/usages/user-management","/usages/dashboard","/usages/coupon-manager","/usages/courses","/configuration/smtp-setup","/usages/media-manager","/configuration/organization-settings","/usages/certificate-management","/usages/about-us-management","/usages/banner-content","/usages/support-ticket","/usages/contact-us","/usages/currency-setting","/usages/language-setup","/usages/support-ticket-instructor","/usages/blogpost-activation","/usages/application-update-setting","/usages/forum-manager","/usages/pages-setting","/usages/quiz-setup","/usages/request-payment","/usages/payment-account-setup","/faq"]}